fc_Oct_shit.py
nq_fir-1.0.1.dist-info/METADATA
nq_fir-1.0.1.dist-info/WHEEL
nq_fir-1.0.1.dist-info/top_level.txt
nq_fir-1.0.1.dist-info/RECORD
