Metadata-Version: 2.1
Name: nq-fir
Version: 1.0.1
Summary: code pass
Home-page: UNKNOWN
Author: HONOR
Author-email: f81471716@163.com
License: UNKNOWN
Platform: UNKNOWN
